{"atlanta_hawks": "ATL", 
"boston_celtics": "BOS", 
"cleveland_cavaliers": "CLE", 
"new_orleans_pelicans": "NOP", 
"chicago_bulls": "CHI", 
"dallas_mavericks": "DAL", 
"denver_nuggets": "DEN", 
"golden_state_warriors": "GSW", 
"houston_rockets": "HOU", 
"los_angeles_clippers": "LAC", 
"los_angeles_lakers": "LAL", 
"miami_heat": "MIA", 
"milwaukee_bucks": "MIL",
"minnesota_timberwolves": "MIN", 
"brooklyn_nets": "BKN", 
"new_york_knicks": "NYK", 
"orlando_magic": "ORL", 
"indiana_pacers": "IND", 
"philadelphia_76ers": "PHI", 
"phoenix_suns": "PHX", 
"portland_trail_blazers": "POR", 
"sacramento_kings": "SAC", 
"san_antonio_spurs": "SAS", 
"oklahoma_city_thunder": "OKC", 
"toronto_raptors": "TOR", 
"utah_jazz": "UTA", 
"memphis_grizzlies": "MEM", 
"washington_wizards": "WAS", 
"detroit_pistons": "DET", 
"charlotte_hornets": "CHA"}